MANIFEST.in
README.md
requirements.txt
setup.py
acss/__init__.py
acss/client.py
acss/db.py
acss/server.py
acss.egg-info/PKG-INFO
acss.egg-info/SOURCES.txt
acss.egg-info/dependency_links.txt
acss.egg-info/entry_points.txt
acss.egg-info/not-zip-safe
acss.egg-info/requires.txt
acss.egg-info/top_level.txt
acss/cli/__init__.py
acss/cli/cron.py
acss/cli/wsgi_service.py