Metadata-Version: 1.1
Name: acss
Version: 0.5.2
Summary: acss
Home-page: https://b.joaoubaldo.com
Author: Joao Coutinho
Author-email: me at joaoubaldo.com
License: UNKNOWN
Keywords: web assetto-corsa dedicated server stats statistics timing
Platform: UNKNOWN
Classifier: Programming Language :: Python
Classifier: Framework :: Pyramid
Classifier: Topic :: Internet :: WWW/HTTP
Classifier: Topic :: Internet :: WWW/HTTP :: WSGI :: Application
